{
  "updatedAt": "2026-04-22T02:37:18.082Z",
  "headline": "지키려는 신한, 뺏으려는 우리 … 서울시금고 둘러싼 은행권 기싸움 한... 등 새마을금고 관련 이슈를 우선 확인할 필요가 있습니다.",
  "categories": {
    "mg": [
      {
        "title": "지키려는 신한, 뺏으려는 우리 … 서울시금고 둘러싼 은행권 기싸움 한...",
        "link": "https://biz.newdaily.co.kr/site/data/html/2026/04/22/2026042200101.html",
        "source": "네이버뉴스",
        "pubDate": "Wed, 22 Apr 2026 11:24:00 +0900",
        "summary": "",
        "term": null
      },
      {
        "title": "51조 ‘서울시 금고’ 두고 맞붙은 신한·우리… “수천억 투입” vs “...",
        "link": "https://n.news.naver.com/mnews/article/366/0001158772?sid=101",
        "source": "네이버뉴스",
        "pubDate": "Wed, 22 Apr 2026 11:01:00 +0900",
        "summary": "",
        "term": null
      },
      {
        "title": "농협· 새마을금고 이어 신협도…부실채권 정리 위한 자산관리회사 설립",
        "link": "https://n.news.naver.com/mnews/article/009/0005669614?sid=101",
        "source": "네이버뉴스",
        "pubDate": "Wed, 22 Apr 2026 10:37:00 +0900",
        "summary": "새마을금고 건전성 관리 흐름과 연결해 볼 수 있는 기사입니다.",
        "term": {
          "word": "Delinquency",
          "meaning": "연체 흐름을 통해 자산건전성 악화 가능성을 읽는 지표"
        }
      },
      {
        "title": "하늘내린 새마을금고 , 인제군 취약계층에 제습기 후원",
        "link": "https://n.news.naver.com/mnews/article/468/0001235767?sid=102",
        "source": "네이버뉴스",
        "pubDate": "Wed, 22 Apr 2026 09:22:00 +0900",
        "summary": "",
        "term": null
      },
      {
        "title": "[Who Is ?] 고영철 신용협동조합중앙회 회장",
        "link": "https://www.businesspost.co.kr/BP?command=article_view&num=436018",
        "source": "네이버뉴스",
        "pubDate": "Wed, 22 Apr 2026 07:02:00 +0900",
        "summary": "새마을금고 조직 운영과 향후 대응 방향을 볼 때 참고할 만한 기사입니다.",
        "term": null
      },
      {
        "title": "새마을금고 중앙회 강원지역본부 후원금 전달식",
        "link": "https://n.news.naver.com/mnews/article/654/0000177011?sid=102",
        "source": "네이버뉴스",
        "pubDate": "Wed, 22 Apr 2026 00:09:00 +0900",
        "summary": "새마을금고 조직 운영과 향후 대응 방향을 볼 때 참고할 만한 기사입니다.",
        "term": null
      },
      {
        "title": "인제하늘내린 새마을금고 제습기 후원",
        "link": "https://n.news.naver.com/mnews/article/654/0000176956?sid=102",
        "source": "네이버뉴스",
        "pubDate": "Wed, 22 Apr 2026 00:07:00 +0900",
        "summary": "",
        "term": null
      },
      {
        "title": "[포토뉴스] 새마을금고 중앙회 강원지역본부 온정 나눔 전달식",
        "link": "https://n.news.naver.com/mnews/article/087/0001188458?sid=101",
        "source": "네이버뉴스",
        "pubDate": "Tue, 21 Apr 2026 17:39:00 +0900",
        "summary": "새마을금고 조직 운영과 향후 대응 방향을 볼 때 참고할 만한 기사입니다.",
        "term": null
      }
    ],
    "otherFinance": [
      {
        "title": "하나 은행 , 민법 개정 맞춤형 '상속·유류분 전략 세미나' 개최",
        "link": "http://www.queen.co.kr/news/articleView.html?idxno=455549",
        "source": "네이버뉴스",
        "pubDate": "Wed, 22 Apr 2026 11:36:00 +0900",
        "summary": "",
        "term": null
      },
      {
        "title": "신한 은행 , 고객 참여형 '나라사랑카드 숏폼 공모전' 개최...총상금 1,600...",
        "link": "http://www.queen.co.kr/news/articleView.html?idxno=455548",
        "source": "네이버뉴스",
        "pubDate": "Wed, 22 Apr 2026 11:36:00 +0900",
        "summary": "",
        "term": null
      },
      {
        "title": "NHN KCP, NH 농협 은행과 ‘스테이블코인 결제 시대’ 연다… 차세대 인프...",
        "link": "https://www.tokenpost.kr/news/blockchain/351976",
        "source": "네이버뉴스",
        "pubDate": "Wed, 22 Apr 2026 11:32:00 +0900",
        "summary": "",
        "term": null
      },
      {
        "title": "NHN KCP, NH농협 은행 과 ‘스테이블코인 결제 시대’ 연다… 차세대 인프...",
        "link": "https://www.tokenpost.kr/news/blockchain/351976",
        "source": "네이버뉴스",
        "pubDate": "Wed, 22 Apr 2026 11:32:00 +0900",
        "summary": "",
        "term": null
      },
      {
        "title": "은행 연합회, 차량 5부제·재택근무 확대",
        "link": "http://www.enewstoday.co.kr/news/articleView.html?idxno=2421842",
        "source": "네이버뉴스",
        "pubDate": "Wed, 22 Apr 2026 11:31:00 +0900",
        "summary": "",
        "term": null
      },
      {
        "title": "\"사람·돈 없어 쩔쩔매던 증권시스템 현대화 한방에\" 삼성SDS '인더스트...",
        "link": "https://www.catchnews.kr/news/articleView.html?idxno=123071",
        "source": "네이버뉴스",
        "pubDate": "Wed, 22 Apr 2026 11:31:00 +0900",
        "summary": "",
        "term": null
      },
      {
        "title": "순천 농협 금당지점, 보이스피싱 예방... 고객 재산 지켜내",
        "link": "https://www.jeonmae.co.kr/news/articleView.html?idxno=1250442",
        "source": "네이버뉴스",
        "pubDate": "Wed, 22 Apr 2026 11:30:00 +0900",
        "summary": "",
        "term": null
      },
      {
        "title": "하나 은행 , '재크의 요술지갑' 어린이 경제 뮤지컬 전국 순회 공연 …AI ...",
        "link": "https://www.public25.com/news/articleView.html?idxno=44743",
        "source": "네이버뉴스",
        "pubDate": "Wed, 22 Apr 2026 11:30:00 +0900",
        "summary": "",
        "term": null
      }
    ],
    "macro": [
      {
        "title": "감사원, 금감원 ‘중간 검사결과 발표’ 정조준…내부선 “발언도 부담...",
        "link": "https://n.news.naver.com/mnews/article/119/0003083127?sid=101",
        "source": "네이버뉴스",
        "pubDate": "Wed, 22 Apr 2026 07:08:00 +0900",
        "summary": "",
        "term": null
      }
    ]
  }
}