{
  "updatedAt": "2026-04-19T02:44:13.171Z",
  "headline": "천안선영 새마을금고 , 천안시복지재단에 2000만 원 후원 등 새마을금고 관련 이슈를 우선 확인할 필요가 있습니다.",
  "categories": {
    "mg": [
      {
        "title": "천안선영 새마을금고 , 천안시복지재단에 2000만 원 후원",
        "link": "https://www.ggilbo.com/news/articleView.html?idxno=1153407",
        "source": "네이버뉴스",
        "pubDate": "Sun, 19 Apr 2026 11:26:00 +0900",
        "summary": "",
        "term": null
      },
      {
        "title": "최고 연 12%... 새마을금고 신생아 적금 ‘인기몰이’",
        "link": "https://n.news.naver.com/mnews/article/011/0004612151?sid=101",
        "source": "네이버뉴스",
        "pubDate": "Sun, 19 Apr 2026 11:05:00 +0900",
        "summary": "",
        "term": null
      },
      {
        "title": "새마을금고 중앙회 충북지역본부. 음성군장애인복지관 지원금 전달",
        "link": "https://www.ccdailynews.com/news/articleView.html?idxno=2411130",
        "source": "네이버뉴스",
        "pubDate": "Sun, 19 Apr 2026 01:54:00 +0900",
        "summary": "새마을금고 조직 운영과 향후 대응 방향을 볼 때 참고할 만한 기사입니다.",
        "term": null
      },
      {
        "title": "전북 새마을금고 경영대상에 '원광 새마을금고 '…9곳 우수 성과 인정",
        "link": "http://www.jeonmin.co.kr/news/articleView.html?idxno=438107",
        "source": "네이버뉴스",
        "pubDate": "Fri, 17 Apr 2026 20:10:00 +0900",
        "summary": "",
        "term": null
      },
      {
        "title": "[기획] 대출 막히고 PF 흔들 '빨간불'… 새마을금고 , 자구책 마련 분주",
        "link": "https://www.startuptoday.co.kr/news/articleView.html?idxno=610207",
        "source": "네이버뉴스",
        "pubDate": "Fri, 17 Apr 2026 19:30:00 +0900",
        "summary": "새마을금고의 수신·여신 운영 흐름과 연결해서 볼 수 있는 기사입니다.",
        "term": null
      }
    ],
    "otherFinance": [
      {
        "title": "[카드 News] 삼성카드·NH 농협 카드·신한카드",
        "link": "http://www.metroseoul.co.kr/article/20260419500112",
        "source": "네이버뉴스",
        "pubDate": "Sun, 19 Apr 2026 11:36:00 +0900",
        "summary": "",
        "term": null
      },
      {
        "title": "우리 은행 , 중견기업 35곳 선정 '4600억 규모 금융 지원' 본격화",
        "link": "https://www.mediafine.co.kr/news/articleView.html?idxno=77594",
        "source": "네이버뉴스",
        "pubDate": "Sun, 19 Apr 2026 11:34:00 +0900",
        "summary": "",
        "term": null
      },
      {
        "title": "우리 은행 , 유망 중견기업 35개사에 최대 300억 지원",
        "link": "http://www.efnews.co.kr/news/articleView.html?idxno=129186",
        "source": "네이버뉴스",
        "pubDate": "Sun, 19 Apr 2026 11:30:00 +0900",
        "summary": "",
        "term": null
      },
      {
        "title": "수출입 은행 , 자체 생성형 AI 플랫폼 'KEXIM AI' 구축",
        "link": "https://n.news.naver.com/mnews/article/014/0005509738?sid=101",
        "source": "네이버뉴스",
        "pubDate": "Sun, 19 Apr 2026 11:27:00 +0900",
        "summary": "타 금융권의 채널 전략 변화를 비교해서 볼 수 있는 기사입니다.",
        "term": null
      },
      {
        "title": "우리 은행 , 유망 기업 35곳에 최대 300억...'생산적 금융 '",
        "link": "https://n.news.naver.com/mnews/article/014/0005509737?sid=101",
        "source": "네이버뉴스",
        "pubDate": "Sun, 19 Apr 2026 11:27:00 +0900",
        "summary": "",
        "term": null
      },
      {
        "title": "천안사랑카드, 'NH포인트'로 충전 가능해진다 ··· 20일부터 서비스",
        "link": "https://www.ggilbo.com/news/articleView.html?idxno=1153396",
        "source": "네이버뉴스",
        "pubDate": "Sun, 19 Apr 2026 11:26:00 +0900",
        "summary": "",
        "term": null
      },
      {
        "title": "'민생지원금 3차 지급일 눈앞' 신청 가능한 카드사와 사용기한",
        "link": "https://www.gukjenews.com/news/articleView.html?idxno=3560596",
        "source": "네이버뉴스",
        "pubDate": "Sun, 19 Apr 2026 11:22:00 +0900",
        "summary": "",
        "term": null
      },
      {
        "title": "천안사랑카드 'NH포인트'로 충전 가능해진다",
        "link": "https://www.ccdailynews.com/news/articleView.html?idxno=2411184",
        "source": "네이버뉴스",
        "pubDate": "Sun, 19 Apr 2026 10:26:00 +0900",
        "summary": "",
        "term": null
      }
    ],
    "macro": [
      {
        "title": "중동 전쟁에 역외 거래에서 변동성 커진 환율… 韓 정규 거래에도 영향",
        "link": "https://n.news.naver.com/mnews/article/366/0001158017?sid=101",
        "source": "네이버뉴스",
        "pubDate": "Sun, 19 Apr 2026 11:25:00 +0900",
        "summary": "",
        "term": null
      },
      {
        "title": "기업대출·고금리·증시 ‘트리플 호재’⋯4대 금융 , 1분기 순익 ‘5조 시...",
        "link": "https://www.viva100.com/article/20260418500189",
        "source": "네이버뉴스",
        "pubDate": "Sun, 19 Apr 2026 10:58:00 +0900",
        "summary": "금리 환경 변화가 금융권 전반에 미치는 영향을 함께 볼 수 있는 기사입니다.",
        "term": null
      },
      {
        "title": "차명대출·가족 몰아주기…광주·전남 금융권 잇딴 비위에 신뢰 '흔들'",
        "link": "https://n.news.naver.com/mnews/article/421/0008897607?sid=102",
        "source": "네이버뉴스",
        "pubDate": "Sun, 19 Apr 2026 08:00:00 +0900",
        "summary": "",
        "term": null
      },
      {
        "title": "메디콕스, 종속회사 중앙셀 대출연장에 91억원 담보 제공 결정",
        "link": "https://www.digitaltoday.co.kr/news/articleView.html?idxno=658115",
        "source": "네이버뉴스",
        "pubDate": "Fri, 17 Apr 2026 18:06:00 +0900",
        "summary": "",
        "term": null
      }
    ]
  }
}